[null,{"name":"Clear","permissions":"MANAGE_MESSAGES","restriction":"1","_id":"YSQOS","actions":[{"info":"0","infoIndex":"1","storage":"1","varName":"1","name":"Store Command Params"},{"storage":"0","varName":"","reason":"","name":"Delete Message"},{"channel":"0","count":"${tempVars(\"1\")}","condition":"0","custom":"","varName":"","name":"Delete Bulk Messages"},{"channel":"0","varName":"","message":"Messages ${tempVars(\"1\")} have been deleted","storage":"1","varName2":"2","name":"Send Message"},{"time":"5","measurement":"1","name":"Wait"},{"storage":"1","varName":"2","reason":"","name":"Delete Message"}]}]